memorious/__init__.py
memorious/cli.py
memorious/core.py
memorious/exc.py
memorious/settings.py
memorious/util.py
memorious/worker.py
memorious/helpers/__init__.py
memorious/helpers/asp.py
memorious/helpers/dates.py
memorious/helpers/key.py
memorious/helpers/ocr.py
memorious/helpers/rule.py
memorious/helpers/ua.py
memorious/logic/__init__.py
memorious/logic/check.py
memorious/logic/context.py
memorious/logic/crawler.py
memorious/logic/http.py
memorious/logic/manager.py
memorious/logic/mime.py
memorious/logic/stage.py
memorious/model/__init__.py
memorious/model/crawl.py
memorious/model/queue.py
memorious/operations/__init__.py
memorious/operations/aleph.py
memorious/operations/clean.py
memorious/operations/db.py
memorious/operations/debug.py
memorious/operations/documentcloud.py
memorious/operations/extract.py
memorious/operations/fetch.py
memorious/operations/ftm.py
memorious/operations/ftp.py
memorious/operations/initializers.py
memorious/operations/parse.py
memorious/operations/store.py
memorious/operations/webdav.py
memorious/tests/__init__.py
memorious/tests/conftest.py
memorious/tests/test_context.py
memorious/tests/test_crawler.py
memorious/tests/test_documentcloud.py
memorious/tests/test_extract.py
memorious/tests/test_http.py
memorious/tests/test_manager.py
memorious/tests/test_operations.py
memorious/tests/test_reporting.py
memorious/tests/test_rule.py
memorious-2.6.5.dist-info/LICENSE
memorious-2.6.5.dist-info/METADATA
memorious-2.6.5.dist-info/WHEEL
memorious-2.6.5.dist-info/entry_points.txt
memorious-2.6.5.dist-info/namespace_packages.txt
memorious-2.6.5.dist-info/top_level.txt
memorious-2.6.5.dist-info/RECORD
