Metadata-Version: 2.1
Name: memorious
Version: 2.6.5
Summary: A minimalistic, recursive web crawling library for Python.
Home-page: http://github.com/alephdata/memorious
Author: Organized Crime and Corruption Reporting Project
Author-email: data@occrp.org
License: MIT
Classifier: Intended Audience :: Developers
Classifier: Operating System :: OS Independent
Classifier: Programming Language :: Python
License-File: LICENSE
Requires-Dist: banal <2.0.0,>=1.0.6
Requires-Dist: click
Requires-Dist: requests[security] >=2.21.0
Requires-Dist: PySocks ==1.7.1
Requires-Dist: requests-ftp
Requires-Dist: lxml >=4
Requires-Dist: normality <3.0.0,>=2.4.0
Requires-Dist: tabulate
Requires-Dist: python-dateutil <3.0.0,>=2.8.2
Requires-Dist: dataset >=1.6.2
Requires-Dist: servicelayer[amazon,google] >=1.21.2
Requires-Dist: pantomime ==0.5.1
Requires-Dist: alephclient >=2.3.5
Requires-Dist: followthemoney >=3.5.8
Requires-Dist: followthemoney-store >=3.0.6
Requires-Dist: dateparser
Requires-Dist: stringcase
Requires-Dist: flask
Requires-Dist: babel
Provides-Extra: dev
Requires-Dist: pytest ; extra == 'dev'
Requires-Dist: pytest-env ; extra == 'dev'
Requires-Dist: pytest-cov ; extra == 'dev'
Requires-Dist: pytest-mock ; extra == 'dev'
Requires-Dist: sphinx ; extra == 'dev'
Requires-Dist: sphinx-rtd-theme ; extra == 'dev'
Requires-Dist: recommonmark ; extra == 'dev'
Provides-Extra: ocr
Requires-Dist: tesserocr ; extra == 'ocr'
